scrunkly/__init__.py
scrunkly-0.1.3.dist-info/METADATA
scrunkly-0.1.3.dist-info/WHEEL
scrunkly-0.1.3.dist-info/entry_points.txt
scrunkly-0.1.3.dist-info/licenses/LICENSE
scrunkly-0.1.3.dist-info/RECORD
