Metadata-Version: 2.3
Name: scrunkly
Version: 0.1.3
Summary: A script runner for the modern age.
Project-URL: Homepage, https://github.com/nokusukun/scrunkly
Project-URL: Issues, https://github.com/nokusukun/scrunkly/issues
Author-email: Noku <noku@onlypa.ws>
License-File: LICENSE
Classifier: License :: OSI Approved :: MIT License
Classifier: Operating System :: OS Independent
Classifier: Programming Language :: Python :: 3
Requires-Python: >=3.8
